odoo/addons/base_wamas_ubl/README.rst
odoo/addons/base_wamas_ubl/__init__.py
odoo/addons/base_wamas_ubl/__manifest__.py
odoo/addons/base_wamas_ubl/i18n/base_wamas_ubl.pot
odoo/addons/base_wamas_ubl/i18n/es.po
odoo/addons/base_wamas_ubl/i18n/it.po
odoo/addons/base_wamas_ubl/lib/dict2wamas
odoo/addons/base_wamas_ubl/lib/generate_sample_results
odoo/addons/base_wamas_ubl/lib/test_dict2wamas
odoo/addons/base_wamas_ubl/lib/test_ubl2wamas
odoo/addons/base_wamas_ubl/lib/test_utils
odoo/addons/base_wamas_ubl/lib/test_wamas2dict
odoo/addons/base_wamas_ubl/lib/test_wamas2ubl
odoo/addons/base_wamas_ubl/lib/test_wamas2wamas
odoo/addons/base_wamas_ubl/lib/ubl2wamas
odoo/addons/base_wamas_ubl/lib/wamas2ubl
odoo/addons/base_wamas_ubl/lib/wamas2wamas
odoo/addons/base_wamas_ubl/lib/wamas/__init__.py
odoo/addons/base_wamas_ubl/lib/wamas/const.py
odoo/addons/base_wamas_ubl/lib/wamas/dict2wamas.py
odoo/addons/base_wamas_ubl/lib/wamas/miniqweb.py
odoo/addons/base_wamas_ubl/lib/wamas/structure.py
odoo/addons/base_wamas_ubl/lib/wamas/ubl2wamas.py
odoo/addons/base_wamas_ubl/lib/wamas/utils.py
odoo/addons/base_wamas_ubl/lib/wamas/wamas2ubl.py
odoo/addons/base_wamas_ubl/lib/wamas/wamas2wamas.py
odoo/addons/base_wamas_ubl/lib/wamas/tests/__init__.py
odoo/addons/base_wamas_ubl/lib/wamas/tests/test_dict2wamas.py
odoo/addons/base_wamas_ubl/lib/wamas/tests/test_ubl2wamas.py
odoo/addons/base_wamas_ubl/lib/wamas/tests/test_utils.py
odoo/addons/base_wamas_ubl/lib/wamas/tests/test_wamas2dict.py
odoo/addons/base_wamas_ubl/lib/wamas/tests/test_wamas2ubl.py
odoo/addons/base_wamas_ubl/lib/wamas/tests/test_wamas2wamas.py
odoo/addons/base_wamas_ubl/lib/wamas/tests/samples/UBL2WAMAS-SAMPLE_AUSK_AUSP-DESPATCH_ADVICE.xml
odoo/addons/base_wamas_ubl/lib/wamas/tests/samples/UBL2WAMAS-SAMPLE_AUSK_AUSP-DESPATCH_ADVICE2.xml
odoo/addons/base_wamas_ubl/lib/wamas/tests/samples/UBL2WAMAS-SAMPLE_AUSK_AUSP.wamas
odoo/addons/base_wamas_ubl/lib/wamas/tests/samples/UBL2WAMAS-SAMPLE_KRETK_KRETP-DESPATCH_ADVICE.xml
odoo_addon_base_wamas_ubl-16.0.1.17.0.dist-info/METADATA
odoo_addon_base_wamas_ubl-16.0.1.17.0.dist-info/WHEEL
odoo_addon_base_wamas_ubl-16.0.1.17.0.dist-info/top_level.txt
odoo_addon_base_wamas_ubl-16.0.1.17.0.dist-info/RECORD
