Metadata-Version: 2.1
Name: odoo-addon-base_wamas_ubl
Version: 16.0.1.17.0
Summary: Base module to aggregate WAMAS - UBL features.
Home-page: https://github.com/OCA/edi
Author: Camptocamp,BCIM,Odoo Community Association (OCA)
Author-email: support@odoo-community.org
License: AGPL-3
Classifier: Programming Language :: Python
Classifier: Framework :: Odoo
Classifier: Framework :: Odoo :: 16.0
Classifier: License :: OSI Approved :: GNU Affero General Public License v3
Classifier: Development Status :: 3 - Alpha
Requires-Python: >=3.10
Requires-Dist: dotty-dict
Requires-Dist: odoo-addon-base-edi<16.1dev,>=16.0dev
Requires-Dist: odoo-addon-base-ubl<16.1dev,>=16.0dev
Requires-Dist: odoo<16.1dev,>=16.0a
Requires-Dist: pytz
Requires-Dist: xmltodict
